cmdbng/cli.py
cmdbng-0.3.22.dist-info/METADATA
cmdbng-0.3.22.dist-info/WHEEL
cmdbng-0.3.22.dist-info/entry_points.txt
cmdbng-0.3.22.dist-info/RECORD
